madplot/__init__.py
madplot/interactive.py
madplot/plot.py
madplot/utils.py
madplot/madx/__init__.py
madplot/madx/builder.py
madplot/madx/engine.py
madplot/madx/parser.py
madplot-0.4.3.dist-info/LICENSE
madplot-0.4.3.dist-info/METADATA
madplot-0.4.3.dist-info/WHEEL
madplot-0.4.3.dist-info/top_level.txt
madplot-0.4.3.dist-info/RECORD
