Metadata-Version: 2.1
Name: madplot
Version: 0.4.3
Summary: Plot MAD output (and more).
Home-page: https://gitlab.com/Dominik1123/madplot
Author: Dominik Vilsmeier
Author-email: d.vilsmeier@gsi.de
License: MIT
Keywords: MAD,MADX,accelerator,design,interface,plot,simulation,visualization
Platform: UNKNOWN
Classifier: Development Status :: 3 - Alpha
Classifier: License :: OSI Approved :: MIT License
Classifier: Programming Language :: Python :: 3 :: Only
Classifier: Programming Language :: Python :: 3.6
Classifier: Programming Language :: Python :: 3.7
Classifier: Topic :: Scientific/Engineering :: Physics
Classifier: Topic :: Scientific/Engineering :: Visualization
Requires-Python: >=3.6
License-File: LICENSE
Requires-Dist: jinja2
Requires-Dist: matplotlib
Requires-Dist: numpy
Requires-Dist: pandas
Requires-Dist: scipy
